chatlan/__init__.py
chatlan/client_app.py
chatlan/commands/__init__.py
chatlan/commands/connect.py
chatlan/commands/init.py
chatlan/exceptions.py
chatlan/main.py
chatlan/message_widget.py
chatlan/server_app.py
chatlan/utils.py
chatlan-0.3.0.dist-info/METADATA
chatlan-0.3.0.dist-info/WHEEL
chatlan-0.3.0.dist-info/entry_points.txt
chatlan-0.3.0.dist-info/licenses/LICENSE
chatlan-0.3.0.dist-info/RECORD
