Metadata-Version: 2.4
Name: chatlan
Version: 0.3.0
Summary: a TUI program to chat with friends on a LAN
License-Expression: MIT
License-File: LICENSE
Keywords: Chat,LAN,TUI,CLI,terminal
Author: gitmobkab
Author-email: richmondaurel77@gmail.com
Requires-Python: >=3.13,<4.0
Classifier: Environment :: Console
Classifier: Programming Language :: Python :: 3
Classifier: Programming Language :: Python :: 3.13
Classifier: Programming Language :: Python :: 3.14
Requires-Dist: textual (>=6.9.0,<7.0.0)
Requires-Dist: typer (>=0.20.0,<0.21.0)
Project-URL: Repository, https://github.com/gitmobkab/ChatLan
